{
  "indexes": [
    {
      "collectionGroup": "listings",
      "queryScope": "COLLECTION",
      "fields": [
        { "fieldPath": "seller", "order": "ASCENDING" },
        { "fieldPath": "createdAt", "order": "DESCENDING" }
      ]
    },
    {
      "collectionGroup": "listings",
      "queryScope": "COLLECTION",
      "fields": [
        { "fieldPath": "itemId", "order": "ASCENDING" },
        { "fieldPath": "seller", "order": "ASCENDING" }
      ]
    },
    {
      "collectionGroup": "listings",
      "queryScope": "COLLECTION",
      "fields": [
        { "fieldPath": "slot", "order": "ASCENDING" },
        { "fieldPath": "createdAt", "order": "DESCENDING" }
      ]
    },
    {
      "collectionGroup": "listings",
      "queryScope": "COLLECTION",
      "fields": [
        { "fieldPath": "slot", "order": "ASCENDING" },
        { "fieldPath": "price", "order": "ASCENDING" }
      ]
    }
  ],
  "fieldOverrides": []
}
